endstone_emoji/__init__.py
endstone_emoji/config.toml
endstone_emoji/emoji_api.py
endstone_emoji/emoji_plugin.py
endstone_emoji-0.0.2.dist-info/METADATA
endstone_emoji-0.0.2.dist-info/WHEEL
endstone_emoji-0.0.2.dist-info/entry_points.txt
endstone_emoji-0.0.2.dist-info/licenses/LICENSE
endstone_emoji-0.0.2.dist-info/RECORD
