Metadata-Version: 2.3
Name: endstone-emoji
Version: 0.0.2
Summary: EmojiNK in endstone
Project-URL: Homepage, https://github.com/endstone-essentials/emoji
Author-email: daoge_cmd <3523206925@qq.com>
Maintainer-email: daoge_cmd <3523206925@qq.com>, Vincent <magicdroidx@gmail.com>
License: MIT License
License-File: LICENSE
Keywords: emoji,endstone,plugin
